LICENSE
pyproject.toml
stackr/__init__.py
stackr-0.1.1.dist-info/LICENSE
stackr-0.1.1.dist-info/METADATA
stackr-0.1.1.dist-info/WHEEL
stackr-0.1.1.dist-info/RECORD
